<annotation><filename>080.jpg</filename><size><width>1845</width><height>750</height><depth>3</depth></size><object><name>vehicle</name><pose>Unspecified</pose><truncated>0</truncated><difficult>0</difficult><bndbox><xmin>311</xmin><ymin>72</ymin><xmax>495</xmax><ymax>423</ymax></bndbox></object><object><name>vehicle</name><pose>Unspecified</pose><truncated>0</truncated><difficult>0</difficult><bndbox><xmin>55</xmin><ymin>44</ymin><xmax>231</xmax><ymax>235</ymax></bndbox></object><object><name>vehicle</name><pose>Unspecified</pose><truncated>0</truncated><difficult>0</difficult><bndbox><xmin>326</xmin><ymin>1089</ymin><xmax>487</xmax><ymax>1186</ymax></bndbox></object><object><name>vehicle</name><pose>Unspecified</pose><truncated>0</truncated><difficult>0</difficult><bndbox><xmin>64</xmin><ymin>1173</ymin><xmax>184</xmax><ymax>1281</ymax></bndbox></object></annotation>